setup.py
datacompare/__init__.py
datacompare.egg-info/PKG-INFO
datacompare.egg-info/SOURCES.txt
datacompare.egg-info/dependency_links.txt
datacompare.egg-info/not-zip-safe
datacompare.egg-info/requires.txt
datacompare.egg-info/top_level.txt