Metadata-Version: 1.0
Name: datacompare
Version: 0.1
Summary: Compare 2 datasets returning row status
Home-page: https://github.com/marcusrehm/data-compare
Author: Marcus Rehm
Author-email: marcus.rehm@gmail.com
License: MIT
Platform: UNKNOWN
